__init__.py
gros_client/__init__.py
gros_client/robot_base.py
gros_client/common/__init__.py
gros_client/common/camera.py
gros_client/common/system.py
gros_client/robot/__init__.py
gros_client/robot/car.py
gros_client/robot/dog.py
gros_client/robot/human.py
demo_robot-1.0.6.dist-info/LICENSE
demo_robot-1.0.6.dist-info/METADATA
demo_robot-1.0.6.dist-info/WHEEL
demo_robot-1.0.6.dist-info/top_level.txt
demo_robot-1.0.6.dist-info/RECORD
