Metadata-Version: 2.1
Name: demo-robot
Version: 1.0.6
Summary: fftai-robot controller sdk
Author: jax
Author-email: jax <ming.li@fftai.com>
License: MIT
Classifier: Programming Language :: Python :: 3
Classifier: License :: OSI Approved :: MIT License
Classifier: Operating System :: OS Independent
Requires-Python: >=3.8
License-File: LICENSE
